<annotation><folder>test_xmls</folder><filename>host-a011_cam0_1234639312851142006.jpeg</filename><path>./imageshost-a011_cam0_1234639312851142006.jpeg</path><source><database>Unknown</database></source><size><width>1224</width><height>1024</height><depth>3</depth></size><segmented>0</segmented><object><name>car</name><pose>Unspecified</pose><truncated>0</truncated><difficult>0</difficult><bndbox><xmin>742.1336002</xmin><ymin>517.881153</ymin><xmax>769.6867226</xmax><ymax>539.0334181</ymax></bndbox></object><object><name>car</name><pose>Unspecified</pose><truncated>0</truncated><difficult>0</difficult><bndbox><xmin>601.5428443</xmin><ymin>512.2176074</ymin><xmax>649.4733893</xmax><ymax>559.1648321</ymax></bndbox></object><object><name>car</name><pose>Unspecified</pose><truncated>0</truncated><difficult>0</difficult><bndbox><xmin>865.6421581</xmin><ymin>515.0396933</ymin><xmax>969.3291812</xmax><ymax>547.1427991</ymax></bndbox></object><object><name>car</name><pose>Unspecified</pose><truncated>0</truncated><difficult>0</difficult><bndbox><xmin>579.2061746</xmin><ymin>520.0390165</ymin><xmax>655.9030218</xmax><ymax>546.079361</ymax></bndbox></object><object><name>car</name><pose>Unspecified</pose><truncated>0</truncated><difficult>0</difficult><bndbox><xmin>-44.88433519</xmin><ymin>506.6332848</ymin><xmax>414.9329301</xmax><ymax>762.9317106</ymax></bndbox></object><object><name>car</name><pose>Unspecified</pose><truncated>0</truncated><difficult>0</difficult><bndbox><xmin>390.1271635</xmin><ymin>523.471851</ymin><xmax>512.774094</xmax><ymax>606.9459439</ymax></bndbox></object><object><name>car</name><pose>Unspecified</pose><truncated>0</truncated><difficult>0</difficult><bndbox><xmin>353.5167012</xmin><ymin>518.0196468</ymin><xmax>449.4042401</xmax><ymax>581.1239379</ymax></bndbox></object><object><name>car</name><pose>Unspecified</pose><truncated>0</truncated><difficult>0</difficult><bndbox><xmin>601.3897291</xmin><ymin>520.0234845</ymin><xmax>663.4478779</xmax><ymax>571.3645751</ymax></bndbox></object><object><name>car</name><pose>Unspecified</pose><truncated>0</truncated><difficult>0</difficult><bndbox><xmin>490.5109759</xmin><ymin>519.9914321</ymin><xmax>535.0510703</xmax><ymax>543.3563196</ymax></bndbox></object><object><name>car</name><pose>Unspecified</pose><truncated>0</truncated><difficult>0</difficult><bndbox><xmin>522.6111099</xmin><ymin>515.1046295</ymin><xmax>573.4248425</xmax><ymax>562.1960767</ymax></bndbox></object><object><name>car</name><pose>Unspecified</pose><truncated>0</truncated><difficult>0</difficult><bndbox><xmin>782.7054611</xmin><ymin>507.5544329</ymin><xmax>883.3607112</xmax><ymax>544.5285836</ymax></bndbox></object><object><name>car</name><pose>Unspecified</pose><truncated>0</truncated><difficult>0</difficult><bndbox><xmin>925.7826411</xmin><ymin>505.1184394</ymin><xmax>1039.903378</xmax><ymax>544.1590257</ymax></bndbox></object><object><name>car</name><pose>Unspecified</pose><truncated>0</truncated><difficult>0</difficult><bndbox><xmin>1107.491228</xmin><ymin>502.6080104</ymin><xmax>1237.518328</xmax><ymax>542.5661744</ymax></bndbox></object><object><name>car</name><pose>Unspecified</pose><truncated>0</truncated><difficult>0</difficult><bndbox><xmin>455.2321125</xmin><ymin>521.1686037</ymin><xmax>510.5850244</xmax><ymax>557.2432146</ymax></bndbox></object><object><name>car</name><pose>Unspecified</pose><truncated>0</truncated><difficult>0</difficult><bndbox><xmin>493.4804397</xmin><ymin>524.6620742</ymin><xmax>564.0599557</xmax><ymax>574.3586367</ymax></bndbox></object><object><name>other_vehicle</name><pose>Unspecified</pose><truncated>0</truncated><difficult>0</difficult><bndbox><xmin>-1008.379095</xmin><ymin>339.2240321</ymin><xmax>202.387405</xmax><ymax>872.5428737</ymax></bndbox></object><object><name>car</name><pose>Unspecified</pose><truncated>0</truncated><difficult>0</difficult><bndbox><xmin>217.8614032</xmin><ymin>516.1348375</ymin><xmax>375.5518081</xmax><ymax>604.0867609</ymax></bndbox></object></annotation>