<annotation><folder>test_xmls</folder><filename>host-a101_cam6_1243095625544000006.jpeg</filename><path>./imageshost-a101_cam6_1243095625544000006.jpeg</path><source><database>Unknown</database></source><size><width>1920</width><height>1080</height><depth>3</depth></size><segmented>0</segmented><object><name>car</name><pose>Unspecified</pose><truncated>0</truncated><difficult>0</difficult><bndbox><xmin>373.0573197</xmin><ymin>944.6593783</ymin><xmax>699.3720403</xmax><ymax>1218.571462</ymax></bndbox></object><object><name>car</name><pose>Unspecified</pose><truncated>0</truncated><difficult>0</difficult><bndbox><xmin>-150.1009357</xmin><ymin>955.4184731</ymin><xmax>50.37948427</xmax><ymax>1086.740283</ymax></bndbox></object><object><name>car</name><pose>Unspecified</pose><truncated>0</truncated><difficult>0</difficult><bndbox><xmin>745.7131144</xmin><ymin>984.7702369</ymin><xmax>851.3534804</xmax><ymax>1071.120071</ymax></bndbox></object><object><name>car</name><pose>Unspecified</pose><truncated>0</truncated><difficult>0</difficult><bndbox><xmin>778.904754</xmin><ymin>901.454951</ymin><xmax>1161.354522</xmax><ymax>1273.359266</ymax></bndbox></object><object><name>car</name><pose>Unspecified</pose><truncated>0</truncated><difficult>0</difficult><bndbox><xmin>962.6215979</xmin><ymin>968.1267878</ymin><xmax>1069.595888</xmax><ymax>1059.459678</ymax></bndbox></object><object><name>car</name><pose>Unspecified</pose><truncated>0</truncated><difficult>0</difficult><bndbox><xmin>1718.938017</xmin><ymin>926.9693304</ymin><xmax>1918.611115</xmax><ymax>1048.350149</ymax></bndbox></object><object><name>car</name><pose>Unspecified</pose><truncated>0</truncated><difficult>0</difficult><bndbox><xmin>137.0753457</xmin><ymin>955.6900971</ymin><xmax>425.3893307</xmax><ymax>1186.70949</ymax></bndbox></object><object><name>car</name><pose>Unspecified</pose><truncated>0</truncated><difficult>0</difficult><bndbox><xmin>4.711570309</xmin><ymin>971.9295402</ymin><xmax>174.6248611</xmax><ymax>1071.703191</ymax></bndbox></object><object><name>car</name><pose>Unspecified</pose><truncated>0</truncated><difficult>0</difficult><bndbox><xmin>621.7365316</xmin><ymin>982.5623717</ymin><xmax>811.1979752</xmax><ymax>1123.481312</ymax></bndbox></object></annotation>