<annotation><folder>test_xmls</folder><filename>host-a004_cam6_1232905207350948006.jpeg</filename><path>./imageshost-a004_cam6_1232905207350948006.jpeg</path><source><database>Unknown</database></source><size><width>2048</width><height>864</height><depth>3</depth></size><segmented>0</segmented><object><name>car</name><pose>Unspecified</pose><truncated>0</truncated><difficult>0</difficult><bndbox><xmin>490.0859733</xmin><ymin>769.5984692</ymin><xmax>680.3063204</xmax><ymax>864.0</ymax></bndbox></object><object><name>car</name><pose>Unspecified</pose><truncated>0</truncated><difficult>0</difficult><bndbox><xmin>1011.580655</xmin><ymin>744.8866373</ymin><xmax>1118.356326</xmax><ymax>841.5128198</ymax></bndbox></object><object><name>car</name><pose>Unspecified</pose><truncated>0</truncated><difficult>0</difficult><bndbox><xmin>1035.866941</xmin><ymin>771.8210412</ymin><xmax>1199.166257</xmax><ymax>864.0</ymax></bndbox></object><object><name>car</name><pose>Unspecified</pose><truncated>0</truncated><difficult>0</difficult><bndbox><xmin>136.0709708</xmin><ymin>773.6281702</ymin><xmax>317.0715274</xmax><ymax>864.0</ymax></bndbox></object><object><name>other_vehicle</name><pose>Unspecified</pose><truncated>0</truncated><difficult>0</difficult><bndbox><xmin>0</xmin><ymin>715.5394916</ymin><xmax>20.19702546</xmax><ymax>864.0</ymax></bndbox></object><object><name>truck</name><pose>Unspecified</pose><truncated>0</truncated><difficult>0</difficult><bndbox><xmin>1782.09605</xmin><ymin>614.063372</ymin><xmax>2048.0</xmax><ymax>864.0</ymax></bndbox></object><object><name>pedestrian</name><pose>Unspecified</pose><truncated>0</truncated><difficult>0</difficult><bndbox><xmin>1337.48097</xmin><ymin>758.5777837</ymin><xmax>1378.245005</xmax><ymax>837.3777904</ymax></bndbox></object><object><name>car</name><pose>Unspecified</pose><truncated>0</truncated><difficult>0</difficult><bndbox><xmin>0</xmin><ymin>769.279773</ymin><xmax>137.3545676</xmax><ymax>864.0</ymax></bndbox></object><object><name>car</name><pose>Unspecified</pose><truncated>0</truncated><difficult>0</difficult><bndbox><xmin>814.3983179</xmin><ymin>749.0817415</ymin><xmax>926.4309346</xmax><ymax>844.8030827</ymax></bndbox></object><object><name>car</name><pose>Unspecified</pose><truncated>0</truncated><difficult>0</difficult><bndbox><xmin>296.9780119</xmin><ymin>769.4140396</ymin><xmax>420.3028459</xmax><ymax>850.0609125</ymax></bndbox></object><object><name>car</name><pose>Unspecified</pose><truncated>0</truncated><difficult>0</difficult><bndbox><xmin>715.9211727</xmin><ymin>751.4350979</ymin><xmax>904.5485327</xmax><ymax>864.0</ymax></bndbox></object><object><name>car</name><pose>Unspecified</pose><truncated>0</truncated><difficult>0</difficult><bndbox><xmin>450.8870937</xmin><ymin>772.6285497</ymin><xmax>573.3777566</xmax><ymax>846.8203001</ymax></bndbox></object></annotation>