<annotation><folder>test_xmls</folder><filename>host-a004_cam5_1232923284867556006.jpeg</filename><path>./imageshost-a004_cam5_1232923284867556006.jpeg</path><source><database>Unknown</database></source><size><width>1224</width><height>1024</height><depth>3</depth></size><segmented>0</segmented><object><name>car</name><pose>Unspecified</pose><truncated>0</truncated><difficult>0</difficult><bndbox><xmin>447.444564</xmin><ymin>542.7284299</ymin><xmax>614.8931441</xmax><ymax>609.5764874</ymax></bndbox></object><object><name>car</name><pose>Unspecified</pose><truncated>0</truncated><difficult>0</difficult><bndbox><xmin>201.8386747</xmin><ymin>522.1743279</ymin><xmax>427.7794291</xmax><ymax>620.3516531</ymax></bndbox></object><object><name>other_vehicle</name><pose>Unspecified</pose><truncated>0</truncated><difficult>0</difficult><bndbox><xmin>1174.863332</xmin><ymin>524.4710587</ymin><xmax>1224.0</xmax><ymax>582.0078004</ymax></bndbox></object><object><name>car</name><pose>Unspecified</pose><truncated>0</truncated><difficult>0</difficult><bndbox><xmin>795.3184905</xmin><ymin>517.9634081</ymin><xmax>971.0440428</xmax><ymax>596.5925192</ymax></bndbox></object><object><name>car</name><pose>Unspecified</pose><truncated>0</truncated><difficult>0</difficult><bndbox><xmin>956.9514213</xmin><ymin>553.6622925</ymin><xmax>1061.447162</xmax><ymax>590.3418633</ymax></bndbox></object><object><name>car</name><pose>Unspecified</pose><truncated>0</truncated><difficult>0</difficult><bndbox><xmin>0</xmin><ymin>525.5289452</ymin><xmax>195.0510713</xmax><ymax>628.9355823</ymax></bndbox></object></annotation>