<annotation><folder>test_xmls</folder><filename>host-a004_cam4_1232842378284193006.jpeg</filename><path>./imageshost-a004_cam4_1232842378284193006.jpeg</path><source><database>Unknown</database></source><size><width>1224</width><height>1024</height><depth>3</depth></size><segmented>0</segmented><object><name>car</name><pose>Unspecified</pose><truncated>0</truncated><difficult>0</difficult><bndbox><xmin>525.4338102</xmin><ymin>512.9307235</ymin><xmax>773.5793248</xmax><ymax>602.1445145</ymax></bndbox></object><object><name>bus</name><pose>Unspecified</pose><truncated>0</truncated><difficult>0</difficult><bndbox><xmin>347.2313095</xmin><ymin>468.5992751</ymin><xmax>601.9588807</xmax><ymax>566.9368781</ymax></bndbox></object><object><name>car</name><pose>Unspecified</pose><truncated>0</truncated><difficult>0</difficult><bndbox><xmin>68.90276824</xmin><ymin>471.9757802</ymin><xmax>343.0767447</xmax><ymax>598.2038481</ymax></bndbox></object><object><name>car</name><pose>Unspecified</pose><truncated>0</truncated><difficult>0</difficult><bndbox><xmin>1070.664953</xmin><ymin>526.8158981</ymin><xmax>1174.827606</xmax><ymax>567.8721047</ymax></bndbox></object><object><name>car</name><pose>Unspecified</pose><truncated>0</truncated><difficult>0</difficult><bndbox><xmin>565.9072701</xmin><ymin>507.4028585</ymin><xmax>759.2480974</xmax><ymax>587.006716</ymax></bndbox></object><object><name>car</name><pose>Unspecified</pose><truncated>0</truncated><difficult>0</difficult><bndbox><xmin>1168.091416</xmin><ymin>513.2571369</ymin><xmax>1527.172177</xmax><ymax>636.4945964</ymax></bndbox></object><object><name>car</name><pose>Unspecified</pose><truncated>0</truncated><difficult>0</difficult><bndbox><xmin>1143.627551</xmin><ymin>519.9418709</ymin><xmax>1260.080667</xmax><ymax>588.6362539</ymax></bndbox></object><object><name>car</name><pose>Unspecified</pose><truncated>0</truncated><difficult>0</difficult><bndbox><xmin>779.2501304</xmin><ymin>520.6944442</ymin><xmax>939.5072652</xmax><ymax>569.6613651</ymax></bndbox></object><object><name>bus</name><pose>Unspecified</pose><truncated>0</truncated><difficult>0</difficult><bndbox><xmin>541.8945237</xmin><ymin>472.0289631</ymin><xmax>838.9269022</xmax><ymax>579.1398572</ymax></bndbox></object><object><name>car</name><pose>Unspecified</pose><truncated>0</truncated><difficult>0</difficult><bndbox><xmin>-71.87000953</xmin><ymin>475.5125324</ymin><xmax>155.340566</xmax><ymax>577.008381</ymax></bndbox></object></annotation>