<annotation><folder>test_xmls</folder><filename>host-a004_cam4_1233955750284193006.jpeg</filename><path>./imageshost-a004_cam4_1233955750284193006.jpeg</path><source><database>Unknown</database></source><size><width>1224</width><height>1024</height><depth>3</depth></size><segmented>0</segmented><object><name>car</name><pose>Unspecified</pose><truncated>0</truncated><difficult>0</difficult><bndbox><xmin>-51.65404694</xmin><ymin>501.8337388</ymin><xmax>47.79062131</xmax><ymax>544.150088</ymax></bndbox></object><object><name>car</name><pose>Unspecified</pose><truncated>0</truncated><difficult>0</difficult><bndbox><xmin>2.70855529</xmin><ymin>509.6588692</ymin><xmax>87.48562701</xmax><ymax>547.2568168</ymax></bndbox></object><object><name>car</name><pose>Unspecified</pose><truncated>0</truncated><difficult>0</difficult><bndbox><xmin>319.5274866</xmin><ymin>512.4511934</ymin><xmax>468.5379654</xmax><ymax>570.5561519</ymax></bndbox></object><object><name>car</name><pose>Unspecified</pose><truncated>0</truncated><difficult>0</difficult><bndbox><xmin>-223.6283319</xmin><ymin>421.5687039</ymin><xmax>746.1312178</xmax><ymax>1029.315833</ymax></bndbox></object></annotation>