<annotation><folder>test_xmls</folder><filename>host-a007_cam6_1234551915950905006.jpeg</filename><path>./imageshost-a007_cam6_1234551915950905006.jpeg</path><source><database>Unknown</database></source><size><width>2048</width><height>864</height><depth>3</depth></size><segmented>0</segmented><object><name>car</name><pose>Unspecified</pose><truncated>0</truncated><difficult>0</difficult><bndbox><xmin>740.0966419</xmin><ymin>782.9659542</ymin><xmax>862.5860954</xmax><ymax>867.6018922</ymax></bndbox></object><object><name>car</name><pose>Unspecified</pose><truncated>0</truncated><difficult>0</difficult><bndbox><xmin>882.1490404</xmin><ymin>787.7438658</ymin><xmax>1059.30375</xmax><ymax>922.450945</ymax></bndbox></object></annotation>