<annotation><folder>test_xmls</folder><filename>host-a004_cam4_1233427015684193006.jpeg</filename><path>./imageshost-a004_cam4_1233427015684193006.jpeg</path><source><database>Unknown</database></source><size><width>1224</width><height>1024</height><depth>3</depth></size><segmented>0</segmented><object><name>other_vehicle</name><pose>Unspecified</pose><truncated>0</truncated><difficult>0</difficult><bndbox><xmin>305.808858</xmin><ymin>485.1386046</ymin><xmax>524.3808785</xmax><ymax>587.9710868</ymax></bndbox></object><object><name>car</name><pose>Unspecified</pose><truncated>0</truncated><difficult>0</difficult><bndbox><xmin>0</xmin><ymin>507.1959463</ymin><xmax>35.75041987</xmax><ymax>550.2021767</ymax></bndbox></object><object><name>car</name><pose>Unspecified</pose><truncated>0</truncated><difficult>0</difficult><bndbox><xmin>137.8688291</xmin><ymin>527.6510065</ymin><xmax>243.1664047</xmax><ymax>564.9116242</ymax></bndbox></object><object><name>car</name><pose>Unspecified</pose><truncated>0</truncated><difficult>0</difficult><bndbox><xmin>219.8954193</xmin><ymin>530.624188</ymin><xmax>338.5252513</xmax><ymax>573.7867793</ymax></bndbox></object><object><name>car</name><pose>Unspecified</pose><truncated>0</truncated><difficult>0</difficult><bndbox><xmin>0</xmin><ymin>499.5809714</ymin><xmax>52.56959792</xmax><ymax>754.5836416</ymax></bndbox></object><object><name>bus</name><pose>Unspecified</pose><truncated>0</truncated><difficult>0</difficult><bndbox><xmin>1.343413806</xmin><ymin>477.4339829</ymin><xmax>179.9633816</xmax><ymax>559.8269455</ymax></bndbox></object></annotation>