<annotation><folder>test_xmls</folder><filename>host-a011_cam6_1235866715951145006.jpeg</filename><path>./imageshost-a011_cam6_1235866715951145006.jpeg</path><source><database>Unknown</database></source><size><width>2048</width><height>864</height><depth>3</depth></size><segmented>0</segmented><object><name>car</name><pose>Unspecified</pose><truncated>0</truncated><difficult>0</difficult><bndbox><xmin>558.6255297</xmin><ymin>750.8288968</ymin><xmax>768.3481379</xmax><ymax>906.9278378</ymax></bndbox></object><object><name>car</name><pose>Unspecified</pose><truncated>0</truncated><difficult>0</difficult><bndbox><xmin>765.1822763</xmin><ymin>792.6022473</ymin><xmax>866.9882246</xmax><ymax>866.8445303</ymax></bndbox></object><object><name>car</name><pose>Unspecified</pose><truncated>0</truncated><difficult>0</difficult><bndbox><xmin>399.0577111</xmin><ymin>766.1240853</ymin><xmax>575.9896239</xmax><ymax>883.1015137</ymax></bndbox></object><object><name>car</name><pose>Unspecified</pose><truncated>0</truncated><difficult>0</difficult><bndbox><xmin>-208.0919808</xmin><ymin>773.3255818</ymin><xmax>142.4821423</xmax><ymax>936.8151471</ymax></bndbox></object><object><name>other_vehicle</name><pose>Unspecified</pose><truncated>0</truncated><difficult>0</difficult><bndbox><xmin>1154.695435</xmin><ymin>580.7766385</ymin><xmax>1511.237923</xmax><ymax>974.2720114</ymax></bndbox></object><object><name>pedestrian</name><pose>Unspecified</pose><truncated>0</truncated><difficult>0</difficult><bndbox><xmin>1596.924715</xmin><ymin>742.5197898</ymin><xmax>1761.921842</xmax><ymax>982.5745534</ymax></bndbox></object><object><name>car</name><pose>Unspecified</pose><truncated>0</truncated><difficult>0</difficult><bndbox><xmin>-33.33106367</xmin><ymin>754.2189758</ymin><xmax>237.8808183</xmax><ymax>911.9385713</ymax></bndbox></object><object><name>car</name><pose>Unspecified</pose><truncated>0</truncated><difficult>0</difficult><bndbox><xmin>803.8054923</xmin><ymin>760.8600793</ymin><xmax>1103.551124</xmax><ymax>1021.862762</ymax></bndbox></object><object><name>car</name><pose>Unspecified</pose><truncated>0</truncated><difficult>0</difficult><bndbox><xmin>1398.861367</xmin><ymin>805.5295946</ymin><xmax>2027.819577</xmax><ymax>1213.230154</ymax></bndbox></object></annotation>