<annotation><folder>test_xmls</folder><filename>host-a011_cam0_1232839963251142006.jpeg</filename><path>./imageshost-a011_cam0_1232839963251142006.jpeg</path><source><database>Unknown</database></source><size><width>1224</width><height>1024</height><depth>3</depth></size><segmented>0</segmented><object><name>car</name><pose>Unspecified</pose><truncated>0</truncated><difficult>0</difficult><bndbox><xmin>501.1000413</xmin><ymin>526.3167173</ymin><xmax>565.5236343</xmax><ymax>575.8649282</ymax></bndbox></object><object><name>car</name><pose>Unspecified</pose><truncated>0</truncated><difficult>0</difficult><bndbox><xmin>0</xmin><ymin>526.7981169</ymin><xmax>158.6143802</xmax><ymax>606.7734402</ymax></bndbox></object><object><name>car</name><pose>Unspecified</pose><truncated>0</truncated><difficult>0</difficult><bndbox><xmin>616.6193734</xmin><ymin>523.7790101</ymin><xmax>676.3251657</xmax><ymax>544.5498522</ymax></bndbox></object><object><name>car</name><pose>Unspecified</pose><truncated>0</truncated><difficult>0</difficult><bndbox><xmin>555.8203532</xmin><ymin>524.687593</ymin><xmax>589.1330036</xmax><ymax>557.0201743</ymax></bndbox></object><object><name>car</name><pose>Unspecified</pose><truncated>0</truncated><difficult>0</difficult><bndbox><xmin>584.4165529</xmin><ymin>525.4959087</ymin><xmax>612.8429251</xmax><ymax>545.9528787</ymax></bndbox></object><object><name>car</name><pose>Unspecified</pose><truncated>0</truncated><difficult>0</difficult><bndbox><xmin>878.8932531</xmin><ymin>516.0862342</ymin><xmax>976.1295205</xmax><ymax>553.2721354</ymax></bndbox></object><object><name>car</name><pose>Unspecified</pose><truncated>0</truncated><difficult>0</difficult><bndbox><xmin>79.05036108</xmin><ymin>527.3498744</ymin><xmax>266.5030086</xmax><ymax>612.3165489</ymax></bndbox></object><object><name>car</name><pose>Unspecified</pose><truncated>0</truncated><difficult>0</difficult><bndbox><xmin>255.1094234</xmin><ymin>532.4274113</ymin><xmax>360.3751688</xmax><ymax>586.6229789</ymax></bndbox></object><object><name>car</name><pose>Unspecified</pose><truncated>0</truncated><difficult>0</difficult><bndbox><xmin>373.7974024</xmin><ymin>533.4458647</ymin><xmax>398.9432699</xmax><ymax>553.4502587</ymax></bndbox></object><object><name>car</name><pose>Unspecified</pose><truncated>0</truncated><difficult>0</difficult><bndbox><xmin>796.2110067</xmin><ymin>519.8590587</ymin><xmax>887.1538612</xmax><ymax>550.6912153</ymax></bndbox></object><object><name>car</name><pose>Unspecified</pose><truncated>0</truncated><difficult>0</difficult><bndbox><xmin>474.0975539</xmin><ymin>530.0614565</ymin><xmax>504.6044695</xmax><ymax>555.4625435</ymax></bndbox></object><object><name>car</name><pose>Unspecified</pose><truncated>0</truncated><difficult>0</difficult><bndbox><xmin>424.8560803</xmin><ymin>531.9813511</ymin><xmax>497.9473638</xmax><ymax>577.4211227</ymax></bndbox></object><object><name>car</name><pose>Unspecified</pose><truncated>0</truncated><difficult>0</difficult><bndbox><xmin>317.9573198</xmin><ymin>535.1411726</ymin><xmax>370.2600689</xmax><ymax>566.4442929</ymax></bndbox></object></annotation>