<annotation><folder>test_xmls</folder><filename>host-a007_cam6_1233524866450905006.jpeg</filename><path>./imageshost-a007_cam6_1233524866450905006.jpeg</path><source><database>Unknown</database></source><size><width>2048</width><height>864</height><depth>3</depth></size><segmented>0</segmented><object><name>car</name><pose>Unspecified</pose><truncated>0</truncated><difficult>0</difficult><bndbox><xmin>1424.267919</xmin><ymin>756.4403383</ymin><xmax>2016.32952</xmax><ymax>864.0</ymax></bndbox></object><object><name>car</name><pose>Unspecified</pose><truncated>0</truncated><difficult>0</difficult><bndbox><xmin>1265.51496</xmin><ymin>818.9780069</ymin><xmax>1505.051814</xmax><ymax>864.0</ymax></bndbox></object><object><name>car</name><pose>Unspecified</pose><truncated>0</truncated><difficult>0</difficult><bndbox><xmin>1140.973584</xmin><ymin>809.7254475</ymin><xmax>1263.274224</xmax><ymax>864.0</ymax></bndbox></object><object><name>car</name><pose>Unspecified</pose><truncated>0</truncated><difficult>0</difficult><bndbox><xmin>926.6167359</xmin><ymin>805.6656071</ymin><xmax>1095.572207</xmax><ymax>864.0</ymax></bndbox></object><object><name>car</name><pose>Unspecified</pose><truncated>0</truncated><difficult>0</difficult><bndbox><xmin>19.46507946</xmin><ymin>765.3206146</ymin><xmax>361.7667696</xmax><ymax>864.0</ymax></bndbox></object><object><name>car</name><pose>Unspecified</pose><truncated>0</truncated><difficult>0</difficult><bndbox><xmin>65.07552498</xmin><ymin>824.7374583</ymin><xmax>601.1698411</xmax><ymax>864.0</ymax></bndbox></object><object><name>car</name><pose>Unspecified</pose><truncated>0</truncated><difficult>0</difficult><bndbox><xmin>1600.257459</xmin><ymin>742.2038423</ymin><xmax>2048.0</xmax><ymax>864.0</ymax></bndbox></object><object><name>car</name><pose>Unspecified</pose><truncated>0</truncated><difficult>0</difficult><bndbox><xmin>1108.050239</xmin><ymin>788.9213438</ymin><xmax>1228.080116</xmax><ymax>864.0</ymax></bndbox></object></annotation>