<annotation><folder>test_xmls</folder><filename>host-a011_cam5_1233522434667719006.jpeg</filename><path>./imageshost-a011_cam5_1233522434667719006.jpeg</path><source><database>Unknown</database></source><size><width>1224</width><height>1024</height><depth>3</depth></size><segmented>0</segmented><object><name>car</name><pose>Unspecified</pose><truncated>0</truncated><difficult>0</difficult><bndbox><xmin>170.8052743</xmin><ymin>538.6955588</ymin><xmax>206.6468556</xmax><ymax>558.5052968</ymax></bndbox></object><object><name>car</name><pose>Unspecified</pose><truncated>0</truncated><difficult>0</difficult><bndbox><xmin>109.2378247</xmin><ymin>536.2345072</ymin><xmax>155.6992923</xmax><ymax>560.7398399</ymax></bndbox></object><object><name>truck</name><pose>Unspecified</pose><truncated>0</truncated><difficult>0</difficult><bndbox><xmin>228.1239631</xmin><ymin>518.5661069</ymin><xmax>331.8713362</xmax><ymax>574.1325427</ymax></bndbox></object><object><name>car</name><pose>Unspecified</pose><truncated>0</truncated><difficult>0</difficult><bndbox><xmin>319.9048688</xmin><ymin>540.1109424</ymin><xmax>386.607335</xmax><ymax>570.8562063</ymax></bndbox></object><object><name>car</name><pose>Unspecified</pose><truncated>0</truncated><difficult>0</difficult><bndbox><xmin>1190.939821</xmin><ymin>534.9877463</ymin><xmax>1224.0</xmax><ymax>574.7881932</ymax></bndbox></object><object><name>car</name><pose>Unspecified</pose><truncated>0</truncated><difficult>0</difficult><bndbox><xmin>0</xmin><ymin>538.5450796</ymin><xmax>23.68074841</xmax><ymax>570.2154106</ymax></bndbox></object><object><name>car</name><pose>Unspecified</pose><truncated>0</truncated><difficult>0</difficult><bndbox><xmin>20.80799047</xmin><ymin>532.2919532</ymin><xmax>124.1606553</xmax><ymax>590.0887125</ymax></bndbox></object><object><name>car</name><pose>Unspecified</pose><truncated>0</truncated><difficult>0</difficult><bndbox><xmin>1145.283268</xmin><ymin>544.6436469</ymin><xmax>1224.0</xmax><ymax>577.8263136</ymax></bndbox></object></annotation>