<annotation><folder>test_xmls</folder><filename>host-a004_cam5_1232842169867556006.jpeg</filename><path>./imageshost-a004_cam5_1232842169867556006.jpeg</path><source><database>Unknown</database></source><size><width>1224</width><height>1024</height><depth>3</depth></size><segmented>0</segmented><object><name>car</name><pose>Unspecified</pose><truncated>0</truncated><difficult>0</difficult><bndbox><xmin>120.6213836</xmin><ymin>558.2769832</ymin><xmax>303.7141065</xmax><ymax>620.584497</ymax></bndbox></object><object><name>car</name><pose>Unspecified</pose><truncated>0</truncated><difficult>0</difficult><bndbox><xmin>-215.53851</xmin><ymin>530.9276908</ymin><xmax>100.3673843</xmax><ymax>632.4057361</ymax></bndbox></object><object><name>car</name><pose>Unspecified</pose><truncated>0</truncated><difficult>0</difficult><bndbox><xmin>681.6680246</xmin><ymin>552.3680309</ymin><xmax>856.0756229</xmax><ymax>616.6981807</ymax></bndbox></object><object><name>car</name><pose>Unspecified</pose><truncated>0</truncated><difficult>0</difficult><bndbox><xmin>1087.981834</xmin><ymin>551.975498</ymin><xmax>1353.544499</xmax><ymax>661.8483859</ymax></bndbox></object><object><name>car</name><pose>Unspecified</pose><truncated>0</truncated><difficult>0</difficult><bndbox><xmin>564.1260389</xmin><ymin>532.6531548</ymin><xmax>885.5462178</xmax><ymax>664.0330299</ymax></bndbox></object><object><name>car</name><pose>Unspecified</pose><truncated>0</truncated><difficult>0</difficult><bndbox><xmin>-240.6228587</xmin><ymin>555.7278283</ymin><xmax>111.0482105</xmax><ymax>651.5375158</ymax></bndbox></object><object><name>car</name><pose>Unspecified</pose><truncated>0</truncated><difficult>0</difficult><bndbox><xmin>966.4876984</xmin><ymin>562.9083985</ymin><xmax>1451.989465</xmax><ymax>796.2407364</ymax></bndbox></object><object><name>car</name><pose>Unspecified</pose><truncated>0</truncated><difficult>0</difficult><bndbox><xmin>1101.209152</xmin><ymin>545.3784912</ymin><xmax>1218.896507</xmax><ymax>599.4017704</ymax></bndbox></object><object><name>car</name><pose>Unspecified</pose><truncated>0</truncated><difficult>0</difficult><bndbox><xmin>1175.004417</xmin><ymin>552.008145</ymin><xmax>1260.282074</xmax><ymax>587.4802499</ymax></bndbox></object><object><name>car</name><pose>Unspecified</pose><truncated>0</truncated><difficult>0</difficult><bndbox><xmin>504.9428651</xmin><ymin>562.0343669</ymin><xmax>576.799988</xmax><ymax>594.143373</ymax></bndbox></object><object><name>car</name><pose>Unspecified</pose><truncated>0</truncated><difficult>0</difficult><bndbox><xmin>1101.361747</xmin><ymin>554.5681419</ymin><xmax>1245.183586</xmax><ymax>609.4198977</ymax></bndbox></object><object><name>car</name><pose>Unspecified</pose><truncated>0</truncated><difficult>0</difficult><bndbox><xmin>750.2192623</xmin><ymin>541.3108495</ymin><xmax>974.0594934</xmax><ymax>621.264842</ymax></bndbox></object><object><name>car</name><pose>Unspecified</pose><truncated>0</truncated><difficult>0</difficult><bndbox><xmin>1216.187645</xmin><ymin>559.676271</ymin><xmax>1299.721258</xmax><ymax>588.5778717</ymax></bndbox></object><object><name>car</name><pose>Unspecified</pose><truncated>0</truncated><difficult>0</difficult><bndbox><xmin>331.6961879</xmin><ymin>553.3271511</ymin><xmax>413.3837576</xmax><ymax>595.3571024</ymax></bndbox></object><object><name>car</name><pose>Unspecified</pose><truncated>0</truncated><difficult>0</difficult><bndbox><xmin>565.0654643</xmin><ymin>559.6237259</ymin><xmax>648.1289031</xmax><ymax>595.8491212</ymax></bndbox></object></annotation>