<annotation><folder>test_xmls</folder><filename>host-a011_cam3_1236037927800995006.jpeg</filename><path>./imageshost-a011_cam3_1236037927800995006.jpeg</path><source><database>Unknown</database></source><size><width>1224</width><height>1024</height><depth>3</depth></size><segmented>0</segmented><object><name>car</name><pose>Unspecified</pose><truncated>0</truncated><difficult>0</difficult><bndbox><xmin>359.0973588</xmin><ymin>477.1020086</ymin><xmax>419.910721</xmax><ymax>496.2823039</ymax></bndbox></object><object><name>car</name><pose>Unspecified</pose><truncated>0</truncated><difficult>0</difficult><bndbox><xmin>672.3691573</xmin><ymin>494.7880459</ymin><xmax>694.2211989</xmax><ymax>510.8467598</ymax></bndbox></object><object><name>car</name><pose>Unspecified</pose><truncated>0</truncated><difficult>0</difficult><bndbox><xmin>414.6223189</xmin><ymin>478.2014041</ymin><xmax>466.1413632</xmax><ymax>497.7358911</ymax></bndbox></object><object><name>car</name><pose>Unspecified</pose><truncated>0</truncated><difficult>0</difficult><bndbox><xmin>869.2414423</xmin><ymin>513.5735498</ymin><xmax>912.0675121</xmax><ymax>538.8620367</ymax></bndbox></object><object><name>car</name><pose>Unspecified</pose><truncated>0</truncated><difficult>0</difficult><bndbox><xmin>911.1511391</xmin><ymin>507.945968</ymin><xmax>969.7164471</xmax><ymax>527.4583969</ymax></bndbox></object><object><name>car</name><pose>Unspecified</pose><truncated>0</truncated><difficult>0</difficult><bndbox><xmin>736.2348742</xmin><ymin>494.4303587</ymin><xmax>944.5977136</xmax><ymax>650.7760012</ymax></bndbox></object><object><name>car</name><pose>Unspecified</pose><truncated>0</truncated><difficult>0</difficult><bndbox><xmin>1008.72969</xmin><ymin>510.5613344</ymin><xmax>1061.940622</xmax><ymax>528.9800633</ymax></bndbox></object><object><name>car</name><pose>Unspecified</pose><truncated>0</truncated><difficult>0</difficult><bndbox><xmin>964.4820233</xmin><ymin>510.9228241</ymin><xmax>1015.548943</xmax><ymax>527.0496667</ymax></bndbox></object><object><name>car</name><pose>Unspecified</pose><truncated>0</truncated><difficult>0</difficult><bndbox><xmin>899.5372747</xmin><ymin>505.4822622</ymin><xmax>955.1410295</xmax><ymax>524.8107533</ymax></bndbox></object><object><name>car</name><pose>Unspecified</pose><truncated>0</truncated><difficult>0</difficult><bndbox><xmin>518.9446572</xmin><ymin>481.7665037</ymin><xmax>574.6956001</xmax><ymax>504.1681211</ymax></bndbox></object><object><name>car</name><pose>Unspecified</pose><truncated>0</truncated><difficult>0</difficult><bndbox><xmin>486.7499326</xmin><ymin>479.3898165</ymin><xmax>544.5959418</xmax><ymax>504.622039</ymax></bndbox></object></annotation>