<annotation><folder>test_xmls</folder><filename>host-a004_cam5_1233427020867556006.jpeg</filename><path>./imageshost-a004_cam5_1233427020867556006.jpeg</path><source><database>Unknown</database></source><size><width>1224</width><height>1024</height><depth>3</depth></size><segmented>0</segmented><object><name>car</name><pose>Unspecified</pose><truncated>0</truncated><difficult>0</difficult><bndbox><xmin>512.5487326</xmin><ymin>544.4651213</ymin><xmax>699.0480259</xmax><ymax>609.6118621</ymax></bndbox></object><object><name>car</name><pose>Unspecified</pose><truncated>0</truncated><difficult>0</difficult><bndbox><xmin>658.4404494</xmin><ymin>545.2293088</ymin><xmax>1460.457707</xmax><ymax>1007.935811</ymax></bndbox></object><object><name>car</name><pose>Unspecified</pose><truncated>0</truncated><difficult>0</difficult><bndbox><xmin>-87.29797411</xmin><ymin>567.6466146</ymin><xmax>130.3527402</xmax><ymax>634.8845922</ymax></bndbox></object><object><name>car</name><pose>Unspecified</pose><truncated>0</truncated><difficult>0</difficult><bndbox><xmin>1124.8617</xmin><ymin>543.1986892</ymin><xmax>1209.086369</xmax><ymax>585.8521141</ymax></bndbox></object><object><name>car</name><pose>Unspecified</pose><truncated>0</truncated><difficult>0</difficult><bndbox><xmin>918.8095513</xmin><ymin>549.1783394</ymin><xmax>1028.133135</xmax><ymax>593.7847608</ymax></bndbox></object><object><name>other_vehicle</name><pose>Unspecified</pose><truncated>0</truncated><difficult>0</difficult><bndbox><xmin>179.8054326</xmin><ymin>498.7267925</ymin><xmax>511.4878495</xmax><ymax>622.7364373</ymax></bndbox></object><object><name>other_vehicle</name><pose>Unspecified</pose><truncated>0</truncated><difficult>0</difficult><bndbox><xmin>666.3657642</xmin><ymin>512.3568603</ymin><xmax>904.3847966</xmax><ymax>604.1242484</ymax></bndbox></object><object><name>other_vehicle</name><pose>Unspecified</pose><truncated>0</truncated><difficult>0</difficult><bndbox><xmin>1032.92028</xmin><ymin>519.1736756</ymin><xmax>1163.249567</xmax><ymax>587.6529395</ymax></bndbox></object><object><name>car</name><pose>Unspecified</pose><truncated>0</truncated><difficult>0</difficult><bndbox><xmin>992.5383886</xmin><ymin>541.304681</ymin><xmax>1299.58449</xmax><ymax>671.5512354</ymax></bndbox></object></annotation>