<annotation><folder>test_xmls</folder><filename>host-a102_cam0_1242755350948786006.jpeg</filename><path>./imageshost-a102_cam0_1242755350948786006.jpeg</path><source><database>Unknown</database></source><size><width>1920</width><height>1080</height><depth>3</depth></size><segmented>0</segmented><object><name>car</name><pose>Unspecified</pose><truncated>0</truncated><difficult>0</difficult><bndbox><xmin>-48.78622947</xmin><ymin>518.1963124</ymin><xmax>640.7199263</xmax><ymax>939.5996882</ymax></bndbox></object><object><name>car</name><pose>Unspecified</pose><truncated>0</truncated><difficult>0</difficult><bndbox><xmin>792.1940029</xmin><ymin>440.9107259</ymin><xmax>1146.359843</xmax><ymax>833.0313825</ymax></bndbox></object><object><name>car</name><pose>Unspecified</pose><truncated>0</truncated><difficult>0</difficult><bndbox><xmin>90.78150048</xmin><ymin>565.0583338</ymin><xmax>467.9670151</xmax><ymax>729.3993683</ymax></bndbox></object><object><name>car</name><pose>Unspecified</pose><truncated>0</truncated><difficult>0</difficult><bndbox><xmin>84.95273743</xmin><ymin>565.7514852</ymin><xmax>218.2908903</xmax><ymax>604.4630228</ymax></bndbox></object><object><name>car</name><pose>Unspecified</pose><truncated>0</truncated><difficult>0</difficult><bndbox><xmin>524.0183865</xmin><ymin>540.2438086</ymin><xmax>647.5247112</xmax><ymax>607.496141</ymax></bndbox></object><object><name>car</name><pose>Unspecified</pose><truncated>0</truncated><difficult>0</difficult><bndbox><xmin>476.1691103</xmin><ymin>542.4477594</ymin><xmax>638.2767254</xmax><ymax>649.3932946</ymax></bndbox></object><object><name>car</name><pose>Unspecified</pose><truncated>0</truncated><difficult>0</difficult><bndbox><xmin>-35.35257017</xmin><ymin>566.4598825</ymin><xmax>86.90993766</xmax><ymax>608.7930825</ymax></bndbox></object><object><name>car</name><pose>Unspecified</pose><truncated>0</truncated><difficult>0</difficult><bndbox><xmin>1091.185854</xmin><ymin>542.0804822</ymin><xmax>1247.982768</xmax><ymax>651.0688349</ymax></bndbox></object><object><name>truck</name><pose>Unspecified</pose><truncated>0</truncated><difficult>0</difficult><bndbox><xmin>647.1030197</xmin><ymin>525.2681295</ymin><xmax>716.6021325</xmax><ymax>579.0770727</ymax></bndbox></object><object><name>car</name><pose>Unspecified</pose><truncated>0</truncated><difficult>0</difficult><bndbox><xmin>186.2540866</xmin><ymin>560.5897501</ymin><xmax>363.5155104</xmax><ymax>633.374789</ymax></bndbox></object><object><name>car</name><pose>Unspecified</pose><truncated>0</truncated><difficult>0</difficult><bndbox><xmin>781.4293641</xmin><ymin>552.7531863</ymin><xmax>867.8614286</xmax><ymax>622.9212592</ymax></bndbox></object><object><name>car</name><pose>Unspecified</pose><truncated>0</truncated><difficult>0</difficult><bndbox><xmin>1118.865541</xmin><ymin>510.4648288</ymin><xmax>1407.126239</xmax><ymax>712.7722992</ymax></bndbox></object><object><name>car</name><pose>Unspecified</pose><truncated>0</truncated><difficult>0</difficult><bndbox><xmin>415.6815889</xmin><ymin>552.7153921</ymin><xmax>518.8585702</xmax><ymax>605.8763172</ymax></bndbox></object><object><name>car</name><pose>Unspecified</pose><truncated>0</truncated><difficult>0</difficult><bndbox><xmin>688.9378449</xmin><ymin>557.2342134</ymin><xmax>821.2492197</xmax><ymax>650.34047</ymax></bndbox></object><object><name>car</name><pose>Unspecified</pose><truncated>0</truncated><difficult>0</difficult><bndbox><xmin>549.1701811</xmin><ymin>557.6843547</ymin><xmax>774.617067</xmax><ymax>695.8604686</ymax></bndbox></object><object><name>car</name><pose>Unspecified</pose><truncated>0</truncated><difficult>0</difficult><bndbox><xmin>947.3629761</xmin><ymin>536.6891889</ymin><xmax>1083.51377</xmax><ymax>671.8746478</ymax></bndbox></object><object><name>car</name><pose>Unspecified</pose><truncated>0</truncated><difficult>0</difficult><bndbox><xmin>664.2540937</xmin><ymin>551.7202331</ymin><xmax>745.8504259</xmax><ymax>609.1323317</ymax></bndbox></object></annotation>