<annotation><folder>test_xmls</folder><filename>host-a101_cam3_1240877603800000006.jpeg</filename><path>./imageshost-a101_cam3_1240877603800000006.jpeg</path><source><database>Unknown</database></source><size><width>1920</width><height>1080</height><depth>3</depth></size><segmented>0</segmented><object><name>car</name><pose>Unspecified</pose><truncated>0</truncated><difficult>0</difficult><bndbox><xmin>557.487743</xmin><ymin>506.5159885</ymin><xmax>683.8228798</xmax><ymax>547.5319964</ymax></bndbox></object><object><name>car</name><pose>Unspecified</pose><truncated>0</truncated><difficult>0</difficult><bndbox><xmin>471.6454975</xmin><ymin>505.6481008</ymin><xmax>615.1380253</xmax><ymax>554.2493621</ymax></bndbox></object><object><name>car</name><pose>Unspecified</pose><truncated>0</truncated><difficult>0</difficult><bndbox><xmin>943.3359377</xmin><ymin>518.2629629</ymin><xmax>1024.472229</xmax><ymax>588.9603514</ymax></bndbox></object><object><name>car</name><pose>Unspecified</pose><truncated>0</truncated><difficult>0</difficult><bndbox><xmin>1596.000049</xmin><ymin>521.515773</ymin><xmax>1752.596647</xmax><ymax>609.7884447</ymax></bndbox></object><object><name>car</name><pose>Unspecified</pose><truncated>0</truncated><difficult>0</difficult><bndbox><xmin>947.7449719</xmin><ymin>516.082608</ymin><xmax>991.6872013</xmax><ymax>551.6122679</ymax></bndbox></object><object><name>car</name><pose>Unspecified</pose><truncated>0</truncated><difficult>0</difficult><bndbox><xmin>835.7069029</xmin><ymin>521.6704152</ymin><xmax>1129.008278</xmax><ymax>780.9659732</ymax></bndbox></object><object><name>car</name><pose>Unspecified</pose><truncated>0</truncated><difficult>0</difficult><bndbox><xmin>644.4048768</xmin><ymin>488.5173934</ymin><xmax>839.7636319</xmax><ymax>637.5065134</ymax></bndbox></object><object><name>car</name><pose>Unspecified</pose><truncated>0</truncated><difficult>0</difficult><bndbox><xmin>1462.697133</xmin><ymin>533.7648269</ymin><xmax>1557.680684</xmax><ymax>608.7048856</ymax></bndbox></object><object><name>motorcycle</name><pose>Unspecified</pose><truncated>0</truncated><difficult>0</difficult><bndbox><xmin>1615.28494</xmin><ymin>542.6487581</ymin><xmax>1817.367812</xmax><ymax>674.1285988</ymax></bndbox></object><object><name>car</name><pose>Unspecified</pose><truncated>0</truncated><difficult>0</difficult><bndbox><xmin>401.859182</xmin><ymin>512.4395006</ymin><xmax>567.7048538</xmax><ymax>564.6889377</ymax></bndbox></object><object><name>car</name><pose>Unspecified</pose><truncated>0</truncated><difficult>0</difficult><bndbox><xmin>1605.456211</xmin><ymin>531.9863662</ymin><xmax>1920.0</xmax><ymax>674.4428154</ymax></bndbox></object></annotation>