<annotation><folder>test_xmls</folder><filename>host-a011_cam6_1234639317451145006.jpeg</filename><path>./imageshost-a011_cam6_1234639317451145006.jpeg</path><source><database>Unknown</database></source><size><width>2048</width><height>864</height><depth>3</depth></size><segmented>0</segmented><object><name>car</name><pose>Unspecified</pose><truncated>0</truncated><difficult>0</difficult><bndbox><xmin>1251.995863</xmin><ymin>755.523391</ymin><xmax>1830.901272</xmax><ymax>864.0</ymax></bndbox></object><object><name>other_vehicle</name><pose>Unspecified</pose><truncated>0</truncated><difficult>0</difficult><bndbox><xmin>0</xmin><ymin>712.9311593</ymin><xmax>181.6812455</xmax><ymax>864.0</ymax></bndbox></object><object><name>car</name><pose>Unspecified</pose><truncated>0</truncated><difficult>0</difficult><bndbox><xmin>496.1878254</xmin><ymin>717.4079607</ymin><xmax>875.0345703</xmax><ymax>864.0</ymax></bndbox></object><object><name>car</name><pose>Unspecified</pose><truncated>0</truncated><difficult>0</difficult><bndbox><xmin>878.7849212</xmin><ymin>682.7362293</ymin><xmax>1346.806884</xmax><ymax>864.0</ymax></bndbox></object><object><name>car</name><pose>Unspecified</pose><truncated>0</truncated><difficult>0</difficult><bndbox><xmin>1720.830879</xmin><ymin>759.7778548</ymin><xmax>1891.619698</xmax><ymax>864.0</ymax></bndbox></object><object><name>car</name><pose>Unspecified</pose><truncated>0</truncated><difficult>0</difficult><bndbox><xmin>0</xmin><ymin>770.1158693</ymin><xmax>233.2545678</xmax><ymax>864.0</ymax></bndbox></object><object><name>car</name><pose>Unspecified</pose><truncated>0</truncated><difficult>0</difficult><bndbox><xmin>0</xmin><ymin>807.2031854</ymin><xmax>378.5464574</xmax><ymax>864.0</ymax></bndbox></object><object><name>car</name><pose>Unspecified</pose><truncated>0</truncated><difficult>0</difficult><bndbox><xmin>735.0322018</xmin><ymin>747.9022076</ymin><xmax>1790.968094</xmax><ymax>864.0</ymax></bndbox></object><object><name>car</name><pose>Unspecified</pose><truncated>0</truncated><difficult>0</difficult><bndbox><xmin>68.9499795</xmin><ymin>704.7705251</ymin><xmax>648.9604092</xmax><ymax>864.0</ymax></bndbox></object><object><name>car</name><pose>Unspecified</pose><truncated>0</truncated><difficult>0</difficult><bndbox><xmin>393.389645</xmin><ymin>763.0395617</ymin><xmax>545.3514915</xmax><ymax>849.4727632</ymax></bndbox></object></annotation>